{
  "column_details":{
    "LINKID":{"dtype":"string"},
    "STA_FROM":{"dtype":"double"},
    "STA_TO":{"dtype":"double"},
    "SEGMENT_LENGTH":{"dtype":"double"},
    "SURVEY_DIREC":{"dtype":"string", "domain":["O", "N"]},
    "SURVEY_YEAR":{"dtype":"integer"},
    "SURVEY_DATE":{"dtype":"date"},
    "DEFL_LONG":{"dtype":"double"},
    "DEFL_LAT":{"dtype":"double"},
    "DEFL_ALT":{"dtype":"double"},
    "ASPHALT_TEMP":{"dtype":"double"},
    "AIR_TEMP":{"dtype":"double"},
    "SURF_TEMP":{"dtype":"double"},
    "LOAD_KG":{"dtype":"double"},
    "LWD_D0":{"dtype":"double"},
    "LWD_D1":{"dtype":"double"},
    "LWD_D2":{"dtype":"double"},
    "EV_D0":{"dtype":"double"},
    "EV_D1":{"dtype":"double"},
    "D0_D2":{"dtype":"double"},
    "ID_KONSULTAN":{"dtype":"integer"},
    "ID_TEAMLEADER":{"dtype":"integer"},
    "ID_ALATSURVEY":{"dtype":"integer"}
  },
  "search_radius":30
}